pytimbre-1.0.2.2.dist-info/METADATA
pytimbre-1.0.2.2.dist-info/WHEEL
pytimbre-1.0.2.2.dist-info/entry_points.txt
pytimbre-1.0.2.2.dist-info/licenses/LICENSE.txt
pytimbre/__init__.py
pytimbre/audio.py
pytimbre/pytimbre_structure.md
pytimbre/spectral/__init__.py
pytimbre/spectral/fundamental_frequency.py
pytimbre/spectral/spectra.py
pytimbre/spectral/spectral_frame_builder.py
pytimbre/spectral/swipe.py
pytimbre/spectral/timbral_model/__init__.py
pytimbre/spectral/timbral_model/timbral_models.py
pytimbre/spectral/timbral_model/timbral_util.py
pytimbre/spectral/time_histories.py
pytimbre/timbre_features/__init__.py
pytimbre/timbre_features/features.py
pytimbre/timbre_features/metrics.mmd
pytimbre/timbre_features/metrics/__init__.py
pytimbre/timbre_features/metrics/equivalent_level.py
pytimbre/timbre_features/metrics/harmonic.py
pytimbre/timbre_features/metrics/impulse.py
pytimbre/timbre_features/metrics/level.py
pytimbre/timbre_features/metrics/room_acoustics.py
pytimbre/timbre_features/metrics/sound_quality.py
pytimbre/timbre_features/metrics/spectral.py
pytimbre/timbre_features/metrics/temporal.py
pytimbre/utilities/__init__.py
pytimbre/utilities/acoustic_weights.py
pytimbre/utilities/audio_analysis_enumerations.py
pytimbre/utilities/audio_filtering.py
pytimbre/utilities/audio_generator.py
pytimbre/utilities/fractional_octave_band.py
pytimbre/utilities/metadata.py
pytimbre/utilities/spectral_functions.py
pytimbre/utilities/timing_functions.py
pytimbre/utilities/yin.py
pytimbre-1.0.2.2.dist-info/RECORD
