Metadata-Version: 2.1
Name: PyTimbre
Version: 1.0.2.2
Summary: Python conversion of Timbre Toolbox
Keywords: machine learning,feature extraction,MATLAB,audio
Author-Email: frankmobley <mobssoft@gmail.com>, "Dr. Frank Mobley" <frank.mobley.1@afrl.af.mil>
License: MIT
Project-URL: Homepage, https://gitlab.com/python-audio-feature-extraction/pytimbre
Project-URL: docs, https://pytimbre.readthedocs.io/en/latest/
Project-URL: documentation, https://pytimbre.readthedocs.io/en/latest/
Requires-Python: >=3.8
Requires-Dist: colorednoise>=2.1.0
Requires-Dist: numpy>=1.21.5
Requires-Dist: pandas>=1.4.3
Requires-Dist: scipy>=1.9.1
Requires-Dist: statsmodels>=0.13.2
Requires-Dist: json5>=0.9.0
Requires-Dist: matplotlib>=3.8.1
Requires-Dist: openpyxl
Requires-Dist: pyloudnorm
Requires-Dist: librosa
Requires-Dist: soundfile
